hifrank/__init__.py
hifrank/__main__.py
hifrank-1.0.0.dist-info/METADATA
hifrank-1.0.0.dist-info/WHEEL
hifrank-1.0.0.dist-info/entry_points.txt
hifrank-1.0.0.dist-info/top_level.txt
hifrank-1.0.0.dist-info/RECORD
