Metadata-Version: 2.1
Name: hifrank
Version: 1.0.0
Summary: Greets someone with the name Frank according to the time of day
Home-page: https://github.com/frankhuurman/hifrank
Author: Frank
Author-email: pypi-frank@protonmail.com
License: MIT
Platform: UNKNOWN
Classifier: License :: OSI Approved :: MIT License
Classifier: Programming Language :: Python :: 3
